CHANGELOG.txt
LICENSE.txt
MANIFEST.in
README.txt
example.py
setup.py
easyvectors.egg-info/PKG-INFO
easyvectors.egg-info/SOURCES.txt
easyvectors.egg-info/dependency_links.txt
easyvectors.egg-info/top_level.txt
vectors/__init__.py